[{"id":1,"first_name":"Ev","last_name":"Eslie","avatar":"https://robohash.org/laudantiumlaborumet.png?size=200x200&set=set1","birthday":"3/10/1945","university":"Tikrit University","company":"Ainyx","ssn":"165-21-4986","color":"#4d540e"},
{"id":2,"first_name":"Audrie","last_name":"Rogerot","avatar":"https://robohash.org/optionecessitatibusex.png?size=200x200&set=set1","birthday":"7/17/1971","university":"University of Science and Technology","company":"BlogXS","ssn":"246-06-6510","color":"#6731b0"},
{"id":3,"first_name":"Roanne","last_name":"Vondrys","avatar":"https://robohash.org/natusautqui.png?size=200x200&set=set1","birthday":"6/5/1934","university":"Millennia Atlantic University","company":"Thoughtblab","ssn":"163-76-8467","color":"#19ff2b"},
{"id":4,"first_name":"Arther","last_name":"Lorrie","avatar":"https://robohash.org/innostrumnon.png?size=200x200&set=set1","birthday":"2/28/1960","university":"Amrita Vishwa Vidyapeetham (Deemed University)","company":"Dablist","ssn":"636-87-0302","color":"#fda279"},
{"id":5,"first_name":"Zane","last_name":"McKue","avatar":"https://robohash.org/avoluptaset.png?size=200x200&set=set1","birthday":"2/11/2005","university":"University of Connecticut at Waterbury","company":"Divanoodle","ssn":"257-52-7023","color":"#ef29a6"},
{"id":6,"first_name":"Temple","last_name":"Grimsdale","avatar":"https://robohash.org/utdoloresfugit.png?size=200x200&set=set1","birthday":"12/13/2010","university":"Dankook University","company":"Aimbo","ssn":"446-79-2625","color":"#189756"},
{"id":7,"first_name":"Nelson","last_name":"Manthorpe","avatar":"https://robohash.org/eligendibeataeofficia.png?size=200x200&set=set1","birthday":"11/24/1945","university":"University of Rajasthan","company":"Yacero","ssn":"308-69-4770","color":"#3f26e6"},
{"id":8,"first_name":"Midge","last_name":"Gatfield","avatar":"https://robohash.org/eterrornihil.png?size=200x200&set=set1","birthday":"7/19/1935","university":"Pontifícia Universidade Católica do Rio Grande do Sul","company":"Snaptags","ssn":"776-86-5908","color":"#da5715"},
{"id":9,"first_name":"Enrique","last_name":"Stain","avatar":"https://robohash.org/praesentiumculpaeos.png?size=200x200&set=set1","birthday":"1/16/1934","university":"Holy Names College","company":"Rooxo","ssn":"552-59-6796","color":"#4fafb0"},
{"id":10,"first_name":"Bren","last_name":"Mirralls","avatar":"https://robohash.org/vitaemaximequi.png?size=200x200&set=set1","birthday":"5/2/1952","university":"Kanto Gakuen University","company":"Aimbu","ssn":"110-93-6323","color":"#3bf299"},
{"id":11,"first_name":"Morissa","last_name":"Tunny","avatar":"https://robohash.org/nemoofficiaitaque.png?size=200x200&set=set1","birthday":"5/18/1996","university":"Japan Women's University","company":"Vitz","ssn":"535-33-5442","color":"#d8f008"},
{"id":12,"first_name":"Vickie","last_name":"Prandi","avatar":"https://robohash.org/culpapraesentiuma.png?size=200x200&set=set1","birthday":"10/15/1981","university":"Mid-America Nazarene University","company":"Jabbersphere","ssn":"522-78-2242","color":"#54d373"},
{"id":13,"first_name":"Tally","last_name":"Velasquez","avatar":"https://robohash.org/voluptasnatusut.png?size=200x200&set=set1","birthday":"4/6/1988","university":"Gettysburg College","company":"Trupe","ssn":"457-65-2027","color":"#437a93"},
{"id":14,"first_name":"Conan","last_name":"Myott","avatar":"https://robohash.org/repudiandaeanimiporro.png?size=200x200&set=set1","birthday":"4/16/2011","university":"Aichi Medical University","company":"Yodo","ssn":"797-47-8774","color":"#661146"},
{"id":15,"first_name":"Jenifer","last_name":"Caddy","avatar":"https://robohash.org/mollitiamagnamet.png?size=200x200&set=set1","birthday":"7/13/1954","university":"Suzhou University","company":"Babbleblab","ssn":"220-59-0703","color":"#0ae8c3"},
{"id":16,"first_name":"Barby","last_name":"Berthomier","avatar":"https://robohash.org/suntfugiatsequi.png?size=200x200&set=set1","birthday":"11/1/1930","university":"Richmond University - The American International University in London","company":"Eare","ssn":"480-05-7311","color":"#0155de"},
{"id":17,"first_name":"Mair","last_name":"Saturley","avatar":"https://robohash.org/repellenduseaaut.png?size=200x200&set=set1","birthday":"11/20/1989","university":"Magnitogorsk State University","company":"Vitz","ssn":"507-69-7748","color":"#dff8f9"},
{"id":18,"first_name":"Steffane","last_name":"Kemmett","avatar":"https://robohash.org/porrooccaecatiasperiores.png?size=200x200&set=set1","birthday":"11/23/1991","university":"Kansai University of International Studies","company":"Quimm","ssn":"627-67-9038","color":"#b7171b"},
{"id":19,"first_name":"Charmion","last_name":"Klewer","avatar":"https://robohash.org/voluptaserrorin.png?size=200x200&set=set1","birthday":"4/11/2011","university":"University of Molise","company":"Jayo","ssn":"177-82-0847","color":"#aca919"},
{"id":20,"first_name":"Kahlil","last_name":"Langlands","avatar":"https://robohash.org/corruptiquivitae.png?size=200x200&set=set1","birthday":"6/28/1987","university":"Koka Women's College","company":"Camido","ssn":"153-91-8748","color":"#a5996f"}]